README.md
setup.py
Crlfi/main.py
Crlfi/payload.py
Crlfi/inculdes/__init__.py
Crlfi/inculdes/bot.py
Crlfi/inculdes/file.py
Crlfi/inculdes/scan.py
Crlfi/inculdes/writefile.py
Crlfi/utils/__init__.py
Crlfi/utils/banner.py
Crlfi/utils/internet_checker.py
Crlfi/utils/url.py
crlfinjection.egg-info/PKG-INFO
crlfinjection.egg-info/SOURCES.txt
crlfinjection.egg-info/dependency_links.txt
crlfinjection.egg-info/entry_points.txt
crlfinjection.egg-info/requires.txt
crlfinjection.egg-info/top_level.txt