Metadata-Version: 2.1
Name: crlfinjection
Version: 0.0.1
Author: @JUTRM
Author-email: <admin@jutrm.com>
Classifier: Programming Language :: Python :: 3
Classifier: Operating System :: Unix
Classifier: Operating System :: MacOS :: MacOS X
Classifier: Operating System :: Microsoft :: Windows
Requires-Dist: argparse
Requires-Dist: requests
